melaxtool
