Metadata-Version: 1.0
Name: melaxtooltest
Version: 0.0.17
Summary: this is simple tool for melaxtech nlp
Home-page: UNKNOWN
Author: melax
Author-email: UNKNOWN
License: UNKNOWN
Platform: UNKNOWN
